examples/printers/call-graph.py
examples/printers/cfg.py
examples/printers/human-summary.py
examples/printers/subroutine-cfg.py
examples/printers/transaction-context.py
plugin_example/rekey_plugin/setup.py
plugin_example/rekey_plugin/tealer_rekey_plugin/__init__.py
plugin_example/rekey_plugin/tealer_rekey_plugin/detectors/__init__.py
plugin_example/rekey_plugin/tealer_rekey_plugin/detectors/rekeyto_stateless.py
plugin_example/template/setup.py
plugin_example/template/tealer_plugin/__init__.py
plugin_example/template/tealer_plugin/detectors/__init__.py
plugin_example/template/tealer_plugin/detectors/example.py
tealer/__init__.py
tealer/__main__.py
tealer/exceptions.py
tealer/tealer.py
tealer/analyses/__init__.py
tealer/analyses/dataflow/__init__.py
tealer/analyses/dataflow/transaction_context/__init__.py
tealer/analyses/dataflow/transaction_context/addr_fields.py
tealer/analyses/dataflow/transaction_context/all_constraints.py
tealer/analyses/dataflow/transaction_context/fee_field.py
tealer/analyses/dataflow/transaction_context/generic.py
tealer/analyses/dataflow/transaction_context/int_fields.py
tealer/analyses/dataflow/transaction_context/txn_types.py
tealer/analyses/dataflow/transaction_context/utils/__init__.py
tealer/analyses/dataflow/transaction_context/utils/group_helpers.py
tealer/analyses/dataflow/transaction_context/utils/key_helpers.py
tealer/analyses/utils/__init__.py
tealer/analyses/utils/stack_ast_builder.py
tealer/detectors/__init__.py
tealer/detectors/abstract_detector.py
tealer/detectors/all_detectors.py
tealer/detectors/anyone_can_delete.py
tealer/detectors/anyone_can_update.py
tealer/detectors/can_close_account.py
tealer/detectors/can_close_asset.py
tealer/detectors/fee_check.py
tealer/detectors/groupsize.py
tealer/detectors/is_deletable.py
tealer/detectors/is_updatable.py
tealer/detectors/rekeyto.py
tealer/detectors/utils.py
tealer/detectors/optimizations/__init__.py
tealer/detectors/optimizations/constant_gtxn.py
tealer-0.1.2.dist-info/LICENSE
tealer-0.1.2.dist-info/METADATA
tealer-0.1.2.dist-info/WHEEL
tealer-0.1.2.dist-info/entry_points.txt
tealer-0.1.2.dist-info/top_level.txt
tealer-0.1.2.dist-info/RECORD
