Metadata-Version: 2.1
Name: tealer
Version: 0.1.2
Summary: Teal analyzer.
Author: Trail of Bits
License: AGPL-3.0
Project-URL: Homepage, https://github.com/crytic/tealer
Requires-Python: >=3.9
License-File: LICENSE
Requires-Dist: prettytable >=0.7.2
Requires-Dist: py-algorand-sdk
Requires-Dist: pycryptodomex
Requires-Dist: requests
Requires-Dist: pyyaml
Provides-Extra: dev
Requires-Dist: pylint ==2.13.4 ; extra == 'dev'
Requires-Dist: black ==22.3.0 ; extra == 'dev'
Requires-Dist: mypy ==0.942 ; extra == 'dev'
Requires-Dist: pytest-cov ; extra == 'dev'
